MANIFEST.in
README.rst
VERSION
requirements.txt
setup.py
harvest/__init__.py
harvest/constants.py
harvest/harvest.py
harvest/metadata.py
python_harvest_oauth.egg-info/PKG-INFO
python_harvest_oauth.egg-info/SOURCES.txt
python_harvest_oauth.egg-info/dependency_links.txt
python_harvest_oauth.egg-info/requires.txt
python_harvest_oauth.egg-info/top_level.txt
python_harvest_oauth.egg-info/zip-safe