Metadata-Version: 1.1
Name: python-harvest-oauth
Version: 0.0.1a0
Summary: Harvest api client
Home-page: https://bitbucket.org/verisage/python-harvest-oauth
Author: Jake Harding
Author-email: jharding@verisage.us
License: MIT License
Keywords: harvestapp timetracking api
Platform: UNKNOWN
Classifier: Development Status :: 3 - Alpha
Classifier: Environment :: Console
Classifier: Intended Audience :: Developers
Classifier: Natural Language :: English
Classifier: Operating System :: POSIX :: Linux
Classifier: Programming Language :: Python :: 2.7
Classifier: Programming Language :: Python :: 3.4
Classifier: Programming Language :: Python :: 3.5
Classifier: Topic :: Software Development :: Libraries
Classifier: Topic :: Internet :: WWW/HTTP :: Site Management
Classifier: Topic :: Utilities
Classifier: License :: OSI Approved :: MIT License
